pyisg-0.1.8.dist-info/METADATA
pyisg-0.1.8.dist-info/WHEEL
pyisg-0.1.8.dist-info/licenses/LICENSE-APACHE
pyisg-0.1.8.dist-info/licenses/LICENSE-MIT
pyisg/__init__.py
pyisg/types.py
pyisg/rust_impl.cpython-313-s390x-linux-gnu.so
pyisg-0.1.8.dist-info/RECORD
