Metadata-Version: 2.4
Name: pyisg
Version: 0.1.8
Classifier: Programming Language :: Rust
Classifier: Programming Language :: Python :: 3.9
Classifier: Programming Language :: Python :: 3.10
Classifier: Programming Language :: Python :: 3.11
Classifier: Programming Language :: Python :: 3.12
Classifier: Programming Language :: Python :: 3.13
Classifier: Programming Language :: Python :: Implementation :: CPython
Classifier: Programming Language :: Python :: Implementation :: PyPy
Classifier: License :: OSI Approved :: MIT License
Classifier: License :: OSI Approved :: Apache Software License
Classifier: Topic :: Scientific/Engineering :: GIS
Requires-Dist: typing-extensions >=4.0.0 ; python_version < '3.11'
License-File: LICENSE-APACHE
License-File: LICENSE-MIT
Summary: Library reading/writing the ISG 2.0 format
Keywords: GIS,ISG,isg file
Author: Kentaro Tatsumi <paqira.2019@gmail.com>
Author-email: Kentaro Tatsumi <paqira.2019@gmail.com>
License: MIT OR Apache-2.0
Requires-Python: >=3.9
Project-URL: Documentation, https://pyisg.readthedocs.io
Project-URL: Issues, https://github.com/paqira/pyisg/issues
Project-URL: Source, https://github.com/paqira/pyisg
